{
  "id": "5654701e",
  "name": "МПСУ",
  "channelLink": "1",
  "created": "2026-03-01T19:28:02.153Z",
  "createdBy": 804636463,
  "techSpecialists": {
    "test_wywunm": {
      "name": "1",
      "contact": "1",
      "tasks": {
        "workspace": {
          "status": "done",
          "photo": null,
          "photos": [
            "prep-uploads/a4d67ad0-b0f4-4cbe-95fa-7b5cbca70a30.jpg",
            "prep-uploads/294c04cb-e8a4-455b-b682-dbe47e083f6e.jpg"
          ]
        },
        "multimedia": {
          "status": "done",
          "panelOk": true,
          "hdmiOk": true,
          "photos": [
            "prep-uploads/baba71a9-54e3-413f-8f8f-f75e678444b7.jpg"
          ]
        },
        "devices": {
          "status": "pending"
        }
      }
    }
  },
  "participants": {}
}